XMWAI/__init__.py
XMWAI/bomb_core.py
XMWAI/core.py
XMWAI/effects_core.py
XMWAI/fortune_core.py
XMWAI/idiom_core.py
XMWAI/magic_core.py
XMWAI/trial_class.py
XMWAI/web_core.py
XMWAI/assets/__init__.py
XMWAI/assets/like.png
XMWAI/file/__init__.py
XMWAI/file/idiom.json
XMWAI/gif/0.gif
XMWAI/gif/1.gif
XMWAI/gif/10.gif
XMWAI/gif/11.gif
XMWAI/gif/12.gif
XMWAI/gif/13.gif
XMWAI/gif/14.gif
XMWAI/gif/15.gif
XMWAI/gif/16.gif
XMWAI/gif/17.gif
XMWAI/gif/18.gif
XMWAI/gif/19.gif
XMWAI/gif/2.gif
XMWAI/gif/20.gif
XMWAI/gif/21.gif
XMWAI/gif/22.gif
XMWAI/gif/23.gif
XMWAI/gif/24.gif
XMWAI/gif/25.gif
XMWAI/gif/26.gif
XMWAI/gif/27.gif
XMWAI/gif/28.gif
XMWAI/gif/29.gif
XMWAI/gif/3.gif
XMWAI/gif/30.gif
XMWAI/gif/31.gif
XMWAI/gif/32.gif
XMWAI/gif/33.gif
XMWAI/gif/34.gif
XMWAI/gif/35.gif
XMWAI/gif/36.gif
XMWAI/gif/37.gif
XMWAI/gif/38.gif
XMWAI/gif/39.gif
XMWAI/gif/4.gif
XMWAI/gif/40.gif
XMWAI/gif/41.gif
XMWAI/gif/42.gif
XMWAI/gif/43.gif
XMWAI/gif/44.gif
XMWAI/gif/45.gif
XMWAI/gif/46.gif
XMWAI/gif/47.gif
XMWAI/gif/48.gif
XMWAI/gif/49.gif
XMWAI/gif/5.gif
XMWAI/gif/50.gif
XMWAI/gif/51.gif
XMWAI/gif/52.gif
XMWAI/gif/53.gif
XMWAI/gif/54.gif
XMWAI/gif/55.gif
XMWAI/gif/56.gif
XMWAI/gif/57.gif
XMWAI/gif/58.gif
XMWAI/gif/59.gif
XMWAI/gif/6.gif
XMWAI/gif/60.gif
XMWAI/gif/61.gif
XMWAI/gif/62.gif
XMWAI/gif/63.gif
XMWAI/gif/64.gif
XMWAI/gif/65.gif
XMWAI/gif/66.gif
XMWAI/gif/67.gif
XMWAI/gif/68.gif
XMWAI/gif/69.gif
XMWAI/gif/7.gif
XMWAI/gif/70.gif
XMWAI/gif/71.gif
XMWAI/gif/72.gif
XMWAI/gif/73.gif
XMWAI/gif/74.gif
XMWAI/gif/75.gif
XMWAI/gif/76.gif
XMWAI/gif/77.gif
XMWAI/gif/78.gif
XMWAI/gif/79.gif
XMWAI/gif/8.gif
XMWAI/gif/80.gif
XMWAI/gif/81.gif
XMWAI/gif/82.gif
XMWAI/gif/83.gif
XMWAI/gif/84.gif
XMWAI/gif/85.gif
XMWAI/gif/9.gif
XMWAI/gif/__init__.py
XMWAI/static/burger.js
XMWAI/static/images/BottomBun.png
XMWAI/static/images/TopBun.png
XMWAI/static/images/beef.png
XMWAI/static/images/bg.jpeg
XMWAI/static/images/bg.png
XMWAI/static/images/cheese.png
XMWAI/static/images/lettuce.png
xmwai-0.5.8.dist-info/licenses/LICENSE.txt
xmwai-0.5.8.dist-info/METADATA
xmwai-0.5.8.dist-info/WHEEL
xmwai-0.5.8.dist-info/top_level.txt
xmwai-0.5.8.dist-info/RECORD
